langchain_encrypted_mongo_memory/EncryptedMongoChatMemory.py
langchain_encrypted_mongo_memory/__init__.py
langchain_encrypted_mongo_memory-1.0.0.dist-info/licenses/LICENSE
langchain_encrypted_mongo_memory-1.0.0.dist-info/METADATA
langchain_encrypted_mongo_memory-1.0.0.dist-info/WHEEL
langchain_encrypted_mongo_memory-1.0.0.dist-info/top_level.txt
langchain_encrypted_mongo_memory-1.0.0.dist-info/RECORD
