Metadata-Version: 2.4
Name: langchain-encrypted-mongo-memory
Version: 1.0.0
Summary: A secure, encrypted MongoDB chat memory for LangChain applications
Author-email: Hemant Kumar <hemant.kumardeveloper@gmail.com>
Maintainer-email: Hemant Kumar <hemant.kumardeveloper@gmail.com>
License: MIT
Project-URL: Homepage, https://github.com/HATAKEkakshi/langchain-encrypted-mongo-memory
Project-URL: Repository, https://github.com/HATAKEkakshi/langchain-encrypted-mongo-memory
Project-URL: Documentation, https://github.com/HATAKEkakshi/langchain-encrypted-mongo-memory#readme
Project-URL: Issues, https://github.com/HATAKEkakshi/langchain-encrypted-mongo-memory/issues
Keywords: langchain,mongodb,encryption,chat-memory,aes,fernet,security,privacy,pii,hipaa,gdpr
Classifier: Development Status :: 5 - Production/Stable
Classifier: Intended Audience :: Developers
Classifier: License :: OSI Approved :: MIT License
Classifier: Operating System :: OS Independent
Classifier: Programming Language :: Python :: 3
Classifier: Programming Language :: Python :: 3.9
Classifier: Programming Language :: Python :: 3.10
Classifier: Programming Language :: Python :: 3.11
Classifier: Programming Language :: Python :: 3.12
Classifier: Topic :: Security :: Cryptography
Classifier: Topic :: Database
Classifier: Topic :: Software Development :: Libraries :: Python Modules
Requires-Python: >=3.9
License-File: LICENSE
Requires-Dist: langchain>=0.1.0
Requires-Dist: langchain-mongodb>=0.1.0
Requires-Dist: langchain-core>=0.1.0
Requires-Dist: pymongo>=4.0.0
Requires-Dist: mores-encryption>=0.1.0
Provides-Extra: dev
Requires-Dist: pytest>=7.0.0; extra == "dev"
Requires-Dist: pytest-cov>=4.0.0; extra == "dev"
Requires-Dist: black>=23.0.0; extra == "dev"
Requires-Dist: flake8>=6.0.0; extra == "dev"
Requires-Dist: mypy>=1.0.0; extra == "dev"
Requires-Dist: python-dotenv>=1.0.0; extra == "dev"
Dynamic: license-file
